<promoData>
	<!-- Top-level promoText will apply to all products. To customise individual products, add a <promoText> inside the appropriate <promo> -->
	<promoText><![CDATA[
		<p>Join or switch to GMF Health and we&#39;ll waive all 2, 3 and 6 month waiting periods on Extras Cover ^</p>
		<p><a class="dialogPop" data-content="<p>^ Take out a combined Hospital and Extras or Extras only policy with GMF by 30 June 2014 and they&#39;ll waive the usual 2, 3 and 6 month waiting periods on your Extras cover. Offer available to new GMF members, even if you are switching from another fund.  A payment on the policy must be made before a claim can be paid.</p>" title="Conditions">^ Conditions</a></p>
	]]></promoText>
	<!-- Top-level discountText will apply to all products. To customise individual products, add a <discountText> inside the appropriate <promo> -->
	<discountText>* GMF offers a discount of 2 weeks premium for customers who choose to select annual payments.</discountText>

	<promo hospital="Complete Hospital">
		<hospitalPDF>health_fund_info/GMF/GMF-056_Complete_Hospital_Cover.pdf</hospitalPDF>
		<extrasPDF></extrasPDF>
	</promo>
	<promo hospital="Complete Hospital" extras="Complete Extras">
		<hospitalPDF>health_fund_info/GMF/GMF-056_Complete_Hospital_Cover.pdf</hospitalPDF>
		<extrasPDF>health_fund_info/GMF/GMF-059_Complete_Extras.pdf</extrasPDF>
	</promo>
	<promo hospital="Complete Hospital" extras="Mid Extras">
		<hospitalPDF>health_fund_info/GMF/GMF-056_Complete_Hospital_Cover.pdf</hospitalPDF>
		<extrasPDF>health_fund_info/GMF/GMF-060_Mid_Extras.pdf</extrasPDF>
	</promo>
	<promo hospital="Complete Hospital" extras="Lite Extras">
		<hospitalPDF>health_fund_info/GMF/GMF-056_Complete_Hospital_Cover.pdf</hospitalPDF>
		<extrasPDF>health_fund_info/GMF/GMF-061_Lite_Extras.pdf</extrasPDF>
	</promo>
	<promo hospital="Mid Hospital">
		<hospitalPDF>health_fund_info/GMF/GMF-057_Mid_Hospital_Cover.pdf</hospitalPDF>
		<extrasPDF></extrasPDF>
	</promo>
	<promo hospital="Mid Hospital" extras="Complete Extras">
		<hospitalPDF>health_fund_info/GMF/GMF-057_Mid_Hospital_Cover.pdf</hospitalPDF>
		<extrasPDF>health_fund_info/GMF/GMF-059_Complete_Extras.pdf</extrasPDF>
	</promo>
	<promo hospital="Mid Hospital" extras="Mid Extras">
		<hospitalPDF>health_fund_info/GMF/GMF-057_Mid_Hospital_Cover.pdf</hospitalPDF>
		<extrasPDF>health_fund_info/GMF/GMF-060_Mid_Extras.pdf</extrasPDF>
	</promo>
	<promo hospital="Mid Hospital" extras="Lite Extras">
		<hospitalPDF>health_fund_info/GMF/GMF-057_Mid_Hospital_Cover.pdf</hospitalPDF>
		<extrasPDF>health_fund_info/GMF/GMF-061_Lite_Extras.pdf</extrasPDF>
	</promo>
	<promo hospital="Lite Hospital">
		<hospitalPDF>health_fund_info/GMF/GMF-058_Lite_Hospital_Cover.pdf</hospitalPDF>
		<extrasPDF></extrasPDF>
	</promo>
	<promo hospital="Lite Hospital" extras="Complete Extras">
		<hospitalPDF>health_fund_info/GMF/GMF-058_Lite_Hospital_Cover.pdf</hospitalPDF>
		<extrasPDF>health_fund_info/GMF/GMF-059_Complete_Extras.pdf</extrasPDF>
	</promo>
	<promo hospital="Lite Hospital" extras="Mid Extras">
		<hospitalPDF>health_fund_info/GMF/GMF-058_Lite_Hospital_Cover.pdf</hospitalPDF>
		<extrasPDF>health_fund_info/GMF/GMF-060_Mid_Extras.pdf</extrasPDF>
	</promo>
	<promo hospital="Lite Hospital" extras="Lite Extras">
		<hospitalPDF>health_fund_info/GMF/GMF-058_Lite_Hospital_Cover.pdf</hospitalPDF>
		<extrasPDF>health_fund_info/GMF/GMF-061_Lite_Extras.pdf</extrasPDF>
	</promo>
	<promo extras="Complete Extras">
		<hospitalPDF></hospitalPDF>
		<extrasPDF>health_fund_info/GMF/GMF-059_Complete_Extras.pdf</extrasPDF>
	</promo>
	<promo extras="Mid Extras">
		<hospitalPDF></hospitalPDF>
		<extrasPDF>health_fund_info/GMF/GMF-060_Mid_Extras.pdf</extrasPDF>
	</promo>
	<promo extras="Lite Extras">
		<hospitalPDF></hospitalPDF>
		<extrasPDF>health_fund_info/GMF/GMF-061_Lite_Extras.pdf</extrasPDF>
	</promo>
</promoData>